punchhole/tcp/__main__.py
punchhole/tstun/__main__.py
punchhole-0.0.2.dist-info/METADATA
punchhole-0.0.2.dist-info/WHEEL
punchhole-0.0.2.dist-info/licenses/LICENSE
punchhole-0.0.2.dist-info/RECORD
