Metadata-Version: 2.4
Name: punchhole
Version: 0.0.2
Summary: Punch TCP connections through NATs and firewalls by simultaneous open, with T-STUN server's assist
Project-URL: Homepage, https://github.com/dxdxdt/punchhole/
Project-URL: Issues, https://github.com/dxdxdt/punchhole/issues
Author-email: David Timber <dxdt@dev.snart.me>
License-File: LICENSE
Classifier: License :: OSI Approved :: Apache Software License
Classifier: Programming Language :: Python :: 3
Classifier: Topic :: System :: Networking
Requires-Python: >=3.9
